{
 "id": "d4b4027c-26ac-4b85-b6a5-7bc6afd2b58b",
 "title": {
  "en": "Boukyaku no Kanata no Rakuen"
 },
 "contentRating": "safe",
 "matches": [
  {
   "id": "d51470e2-3c32-4516-b614-5ce763ae57a1",
   "title": {
    "en": "Kagenashi no Koibito"
   },
   "contentRating": "safe",
   "score": 0.33028406,
   "languages": [
    "en"
   ]
  },
  {
   "id": "df7f1547-5c7f-42fc-8c77-e98ca1b65abe",
   "title": {
    "en": "A Happy Child"
   },
   "contentRating": "safe",
   "score": 0.31472218,
   "languages": [
    "en"
   ]
  },
  {
   "id": "8c4bdce6-6fea-464e-8351-36b7fa9f2deb",
   "title": {
    "en": "Lega no 13"
   },
   "contentRating": "safe",
   "score": 0.31159982,
   "languages": [
    "en"
   ]
  },
  {
   "id": "19796d23-c371-4f80-961a-fda048a47578",
   "title": {
    "en": "Private Detective Story"
   },
   "contentRating": "safe",
   "score": 0.30942222,
   "languages": [
    "en"
   ]
  },
  {
   "id": "cb6e0cf7-db28-4653-bf0b-286f0ffa5550",
   "title": {
    "en": "Playboy no Hatsukoi"
   },
   "contentRating": "safe",
   "score": 0.30803683,
   "languages": [
    "en"
   ]
  },
  {
   "id": "417b2342-7366-4596-9944-45caa21314ce",
   "title": {
    "en": "Scratch!!"
   },
   "contentRating": "safe",
   "score": 0.3076999,
   "languages": [
    "en"
   ]
  },
  {
   "id": "a13b0c38-ea2c-483d-aa1e-95882f19abb6",
   "title": {
    "en": "Memories -Life-"
   },
   "contentRating": "safe",
   "score": 0.3044165,
   "languages": [
    "en"
   ]
  },
  {
   "id": "ded2f940-82c5-4ba4-acea-4c835dcb950c",
   "title": {
    "en": "To the Stage of Love With the Sheikh"
   },
   "contentRating": "safe",
   "score": 0.30319345,
   "languages": [
    "en"
   ]
  },
  {
   "id": "fc2c0867-f85c-4ce3-95c5-9da54ef03330",
   "title": {
    "en": "Genso Ginekokurasy"
   },
   "contentRating": "safe",
   "score": 0.30267057,
   "languages": [
    "en",
    "pt-br"
   ]
  },
  {
   "id": "acb29589-1369-4982-9756-60450a66b645",
   "title": {
    "en": "The Unintentionally Ideal Adopted Daughter"
   },
   "contentRating": "safe",
   "score": 0.30206576,
   "languages": [
    "en"
   ]
  },
  {
   "id": "a1eeca2d-8f52-4245-9e7b-07de4d23aa73",
   "title": {
    "en": "The Destroyer Fell in Love with Me"
   },
   "contentRating": "safe",
   "score": 0.30080864,
   "languages": [
    "pl",
    "en"
   ]
  },
  {
   "id": "d39c6c91-755e-4ae0-8d98-221ba70d8949",
   "title": {
    "en": "Catch! Love"
   },
   "contentRating": "safe",
   "score": 0.30045938,
   "languages": [
    "en"
   ]
  },
  {
   "id": "e1847df1-db22-4279-95e2-9dbbbd1bbfbc",
   "title": {
    "en": "Father, I Don't Want This Marriage!"
   },
   "contentRating": "safe",
   "score": 0.29967824,
   "languages": [
    "ru",
    "pt-br",
    "en",
    "fr",
    "vi",
    "uk",
    "my",
    "es",
    "pl",
    "id"
   ]
  },
  {
   "id": "bfcc8c6d-b846-44ee-ae29-54360fdeef47",
   "title": {
    "en": "Pink Blossoms Mirror Your Beauty"
   },
   "contentRating": "safe",
   "score": 0.29936364,
   "languages": [
    "en"
   ]
  },
  {
   "id": "210e8cdc-d201-4240-9d3a-1958f137c05b",
   "title": {
    "en": "A Cursed Girl's Bible"
   },
   "contentRating": "safe",
   "score": 0.29907042,
   "languages": [
    "en"
   ]
  },
  {
   "id": "842c1d46-7c7b-4b99-9007-8a2b150627cd",
   "title": {
    "en": "The Children of the Mountain"
   },
   "contentRating": "safe",
   "score": 0.2981732,
   "languages": [
    "en"
   ]
  }
 ],
 "updatedAt": "2023-12-10T01:08:32+00:00"
}