{
 "id": "5b5260d9-af27-41b7-a178-13d08518ed66",
 "title": {
  "en": "The Crown Amidst Darkness"
 },
 "contentRating": "safe",
 "matches": [
  {
   "id": "8a333456-6740-4e84-9991-f77d8a845b4e",
   "title": {
    "en": "Mortal Metal Shibagane"
   },
   "contentRating": "safe",
   "score": 0.30747828,
   "languages": [
    "en"
   ]
  },
  {
   "id": "af454a9c-5006-456b-b6f6-d23e8f84a8e7",
   "title": {
    "en": "Yami ni Naku Oni"
   },
   "contentRating": "safe",
   "score": 0.3027161,
   "languages": [
    "en"
   ]
  },
  {
   "id": "229eb307-021e-4062-8d39-94422da2671e",
   "title": {
    "en": "Tail Star"
   },
   "contentRating": "safe",
   "score": 0.29945958,
   "languages": [
    "pl",
    "en",
    "es",
    "pt-br"
   ]
  },
  {
   "id": "871cd7b7-8212-45d3-b505-6663d0d9cb1f",
   "title": {
    "en": "FREAKS"
   },
   "contentRating": "safe",
   "score": 0.28138897,
   "languages": [
    "en",
    "ru",
    "it",
    "th",
    "hu",
    "fr"
   ]
  },
  {
   "id": "390009ac-c723-43d6-a146-84129eeddb93",
   "title": {
    "en": "Yongbyeong Maluhan"
   },
   "contentRating": "safe",
   "score": 0.27864492,
   "languages": [
    "en",
    "ar"
   ]
  },
  {
   "id": "14ccc74b-43d1-4d9f-84cc-de38eef8c40d",
   "title": {
    "en": "Gate"
   },
   "contentRating": "safe",
   "score": 0.25669697,
   "languages": [
    "en"
   ]
  },
  {
   "id": "463b32af-1ddc-48db-a5e4-4799c8a2e412",
   "title": {
    "en": "Rakshasa Street"
   },
   "contentRating": "safe",
   "score": 0.24948129,
   "languages": [
    "fr",
    "en",
    "pl",
    "pt-br"
   ]
  },
  {
   "id": "21b18592-8925-466b-b909-071b52676a38",
   "title": {
    "en": "Teiden Shoujo to Hanemushi no Orchestra"
   },
   "contentRating": "safe",
   "score": 0.24896532,
   "languages": [
    "en"
   ]
  },
  {
   "id": "09a5f228-f6b2-42a0-9d37-f661ebc6ad35",
   "title": {
    "en": "Hatenkou Yuugi"
   },
   "contentRating": "safe",
   "score": 0.2426827,
   "languages": [
    "en",
    "pl"
   ]
  },
  {
   "id": "62483bf6-e4c2-4aaf-bf53-fc822ba21428",
   "title": {
    "en": "Knight Run - Father's Day"
   },
   "contentRating": "safe",
   "score": 0.23575076,
   "languages": [
    "en"
   ]
  },
  {
   "id": "29fc67d9-d3e4-4d0a-80d9-dfee5d87917d",
   "title": {
    "en": "GOD EATER - Kyuuseishu no Kikan"
   },
   "contentRating": "safe",
   "score": 0.23519187,
   "languages": [
    "es",
    "en"
   ]
  },
  {
   "id": "5c865add-2f78-4903-aa2b-4270690aca34",
   "title": {
    "en": "Savior"
   },
   "contentRating": "safe",
   "score": 0.2327598,
   "languages": [
    "en",
    "it"
   ]
  },
  {
   "id": "dcb9341c-ecb1-4086-aad8-c62ac7b9ab7e",
   "title": {
    "en": "Trace 2.0"
   },
   "contentRating": "safe",
   "score": 0.23256548,
   "languages": [
    "en"
   ]
  },
  {
   "id": "534ba0eb-8d04-4047-8aef-c965ec2ce5c9",
   "title": {
    "en": "Colossus Order"
   },
   "contentRating": "safe",
   "score": 0.23217086,
   "languages": [
    "pt-br",
    "en"
   ]
  },
  {
   "id": "bb865d49-0dd4-49b2-b2a8-6b609e3bba4a",
   "title": {
    "en": "Ana no Mujina"
   },
   "contentRating": "safe",
   "score": 0.23171543,
   "languages": [
    "en",
    "it",
    "es-la",
    "es"
   ]
  },
  {
   "id": "34e45b02-b5c8-4a4b-a21a-7b5059391dc8",
   "title": {
    "en": "To Your Eternity"
   },
   "contentRating": "safe",
   "score": 0.23094384,
   "languages": [
    "ru",
    "pt-br",
    "es",
    "en",
    "es-la",
    "tr",
    "mn",
    "uk"
   ]
  }
 ],
 "updatedAt": "2023-12-10T01:03:23+00:00"
}