{
 "id": "2648461f-41c8-4648-89a1-de7dc9378c8c",
 "title": {
  "en": "Yajuu to Hanayome"
 },
 "contentRating": "safe",
 "matches": [
  {
   "id": "2c7d784f-cb8c-49c2-999e-ab9f2f6453ed",
   "title": {
    "en": "Best Couple"
   },
   "contentRating": "safe",
   "score": 0.2945572,
   "languages": [
    "en"
   ]
  },
  {
   "id": "3385da2a-44e3-40e5-9b83-26c36b13d718",
   "title": {
    "en": "Sakasama no Kimi"
   },
   "contentRating": "safe",
   "score": 0.2857143,
   "languages": [
    "it",
    "fr",
    "en"
   ]
  },
  {
   "id": "43ac0fc3-bb76-40fd-aee5-8489eda4b84d",
   "title": {
    "en": "Oseyo, Hatsukoi"
   },
   "contentRating": "safe",
   "score": 0.2857143,
   "languages": [
    "en"
   ]
  },
  {
   "id": "3869d971-abef-4d68-8074-14f171a760a6",
   "title": {
    "en": "Kimi no Ai de Motenashite"
   },
   "contentRating": "safe",
   "score": 0.2857143,
   "languages": [
    "pt-br"
   ]
  },
  {
   "id": "5b5cd8e5-46a6-41be-9774-d90d4add4a0a",
   "title": {
    "en": "Akuma no Yuuwaku ni, Amaku to Rokeru"
   },
   "contentRating": "safe",
   "score": 0.2857143,
   "languages": [
    "pl",
    "pt-br"
   ]
  },
  {
   "id": "9bb430cd-73d0-4eb1-b419-caed206e6dfd",
   "title": {
    "en": "Three Feminine Sisters"
   },
   "contentRating": "safe",
   "score": 0.2857143,
   "languages": [
    "en",
    "ar"
   ]
  },
  {
   "id": "167689d9-f80e-4ffe-8f59-44d0b41a5f4f",
   "title": {
    "en": "Hand-in-Hand Lovers"
   },
   "contentRating": "safe",
   "score": 0.2857143,
   "languages": [
    "en",
    "pl"
   ]
  },
  {
   "id": "a6588032-93ef-4074-82d0-2ba684125227",
   "title": {
    "en": "Android Dilemma"
   },
   "contentRating": "safe",
   "score": 0.2857143,
   "languages": [
    "en"
   ]
  },
  {
   "id": "8114e8f7-159d-490a-858b-eba765a20f93",
   "title": {
    "en": "Yuki no Koi"
   },
   "contentRating": "safe",
   "score": 0.2857143,
   "languages": [
    "en"
   ]
  },
  {
   "id": "8305911a-7aa9-4537-9d5d-74bc299bf8f0",
   "title": {
    "en": "Otome ni Nante Naremasen"
   },
   "contentRating": "safe",
   "score": 0.2857143,
   "languages": [
    "pt-br",
    "en"
   ]
  },
  {
   "id": "db1840a0-c263-4436-a152-36ea85f4f9e9",
   "title": {
    "en": "White Carol"
   },
   "contentRating": "safe",
   "score": 0.2857143,
   "languages": [
    "pt-br"
   ]
  },
  {
   "id": "bc5735b4-1977-4c6e-b3cd-244a4a836130",
   "title": {
    "en": "Shoujo Ningyo"
   },
   "contentRating": "safe",
   "score": 0.2857143,
   "languages": [
    "en"
   ]
  },
  {
   "id": "49cd9c08-9a2a-4290-9936-a4522b23bff4",
   "title": {
    "en": "Oazuke Shitsuji"
   },
   "contentRating": "safe",
   "score": 0.2857143,
   "languages": [
    "pt-br",
    "en",
    "fr"
   ]
  },
  {
   "id": "bbe3d360-dc89-41d2-8b40-a6f02a4b1a00",
   "title": {
    "en": "Ichinen no Koi wa Gantan ni Ari"
   },
   "contentRating": "safe",
   "score": 0.2857143,
   "languages": [
    "pt-br"
   ]
  },
  {
   "id": "4b85991b-ee4e-4f72-9016-b9ccca09d1a7",
   "title": {
    "en": "No Use Crying Over Spilt Milk"
   },
   "contentRating": "safe",
   "score": 0.2857143,
   "languages": [
    "en",
    "pt-br"
   ]
  },
  {
   "id": "08df1856-3103-4b33-80c3-4c45f9079fc8",
   "title": {
    "en": "Hot Cherry"
   },
   "contentRating": "safe",
   "score": 0.2857143,
   "languages": [
    "en",
    "fr"
   ]
  }
 ],
 "updatedAt": "2023-12-10T01:01:13+00:00"
}