{
 "id": "8725a979-ee7d-47df-a288-a2db107c1734",
 "title": {
  "en": "G'day"
 },
 "contentRating": "safe",
 "matches": [
  {
   "id": "f79104d6-a3b5-46a4-914e-85a988949298",
   "title": {
    "en": "Sister War"
   },
   "contentRating": "safe",
   "score": 0.26088995,
   "languages": [
    "en"
   ]
  },
  {
   "id": "bf23d8f0-ea3f-4ced-bfd3-a589ba487bb8",
   "title": {
    "en": "Oneichan to Issho"
   },
   "contentRating": "safe",
   "score": 0.24991783,
   "languages": [
    "en"
   ]
  },
  {
   "id": "934e9693-31f5-4469-b7a7-c27839d777e6",
   "title": {
    "en": "Little Sister"
   },
   "contentRating": "safe",
   "score": 0.24553709,
   "languages": [
    "en"
   ]
  },
  {
   "id": "3f5bc21d-6575-4fe0-b03f-50c8bb88dc6b",
   "title": {
    "en": "Unhinged"
   },
   "contentRating": "safe",
   "score": 0.23675033,
   "languages": [
    "en"
   ]
  },
  {
   "id": "a972aebe-50fb-4dfe-8f61-0150f3659467",
   "title": {
    "en": "An Unseemly Lady"
   },
   "contentRating": "safe",
   "score": 0.22165705,
   "languages": [
    "pt-br",
    "en"
   ]
  },
  {
   "id": "52a572bc-41cc-4922-a650-0de582376f87",
   "title": {
    "en": "No Rose Without Thorns"
   },
   "contentRating": "safe",
   "score": 0.2197999,
   "languages": [
    "en"
   ]
  },
  {
   "id": "af163267-a8d4-41d2-a189-80bda3ebb27e",
   "title": {
    "en": "Honey, i´m home."
   },
   "contentRating": "safe",
   "score": 0.21636555
  },
  {
   "id": "9b9317b4-9d65-47b1-b169-f189a80bfb12",
   "title": {
    "en": "The Teacher Got Killed"
   },
   "contentRating": "safe",
   "score": 0.21636555
  },
  {
   "id": "e10e4299-6b38-4923-8230-4e384e559634",
   "title": {
    "en": "A Story About a High School Girl Staying Over"
   },
   "contentRating": "safe",
   "score": 0.21341561,
   "languages": [
    "it",
    "vi",
    "en",
    "id"
   ]
  },
  {
   "id": "8c03ce43-04ab-438b-82c0-28c90a92afd9",
   "title": {
    "en": "Blood Ties"
   },
   "contentRating": "safe",
   "score": 0.21254987,
   "languages": [
    "en"
   ]
  },
  {
   "id": "711c7ca2-e528-4f9a-bc7b-936075cdc0ed",
   "title": {
    "en": "House of Riddles"
   },
   "contentRating": "safe",
   "score": 0.20592506,
   "languages": [
    "en"
   ]
  },
  {
   "id": "93667e0c-bbb5-405e-8698-3539a3c994fc",
   "title": {
    "en": "The Saviour's Time"
   },
   "contentRating": "safe",
   "score": 0.20504722,
   "languages": [
    "en",
    "ru",
    "pt-br"
   ]
  },
  {
   "id": "b5e63a2f-f4bc-4c3d-8b25-7b137385abb3",
   "title": {
    "en": "Reborn to Be a Movie Queen"
   },
   "contentRating": "safe",
   "score": 0.20366086,
   "languages": [
    "en"
   ]
  },
  {
   "id": "5abf36e6-b42e-4840-896b-b4b22b17fcd7",
   "title": {
    "en": "Kamisama, Kisama wo Koroshitai."
   },
   "contentRating": "safe",
   "score": 0.20290072,
   "languages": [
    "en"
   ]
  },
  {
   "id": "4ac4c19f-28a9-4f97-bcb7-e9bbc9b33092",
   "title": {
    "en": "Furachi na Sister"
   },
   "contentRating": "safe",
   "score": 0.20185445
  },
  {
   "id": "6afeec8e-6d75-4feb-9fe6-0255bcaf0c1a",
   "title": {
    "en": "The Bethlem of Magicians"
   },
   "contentRating": "safe",
   "score": 0.1995629,
   "languages": [
    "en"
   ]
  }
 ],
 "updatedAt": "2023-12-10T01:05:13+00:00"
}