{
 "id": "a6c63ce1-359e-498d-aabf-2b5ce4d02a02",
 "title": {
  "en": "Kiba no Tabishounin - The Arms Peddler"
 },
 "contentRating": "safe",
 "matches": [
  {
   "id": "0aa2520a-a18f-406d-8908-32cec22b88ac",
   "title": {
    "en": "Kono Sekai ga Izure Horobu Koto wo, Ore dake ga Shitte Iru"
   },
   "contentRating": "safe",
   "score": 0.21031399,
   "languages": [
    "en",
    "id"
   ]
  },
  {
   "id": "229eb307-021e-4062-8d39-94422da2671e",
   "title": {
    "en": "Tail Star"
   },
   "contentRating": "safe",
   "score": 0.19247894,
   "languages": [
    "pl",
    "en",
    "es",
    "pt-br"
   ]
  },
  {
   "id": "f1d65976-1ed7-4843-bb03-fa7a5cbe0715",
   "title": {
    "en": "Grandeek ReeL"
   },
   "contentRating": "safe",
   "score": 0.18879525,
   "languages": [
    "en"
   ]
  },
  {
   "id": "04c875aa-7b61-4b00-8c39-d753d0b6bc6d",
   "title": {
    "en": "A Genius' Isekai Overlord Legend - Fist of the North Star: Amiba Gaiden - Even if I Go to Another World, I Am a Genius!! Huh? Was I Mistaken..."
   },
   "contentRating": "safe",
   "score": 0.18719515,
   "languages": [
    "en"
   ]
  },
  {
   "id": "6d4e768d-d68a-449f-8983-f7acbc160d9c",
   "title": {
    "en": "Kara no Kyoukai - The Garden of Sinners"
   },
   "contentRating": "safe",
   "score": 0.1864897,
   "languages": [
    "ru",
    "en",
    "fr",
    "es-la",
    "pl"
   ]
  },
  {
   "id": "c9494b8e-9cf0-4d52-a99c-7db2ef255e73",
   "title": {
    "en": "Meiou-sama ga Tooru no desu yo!"
   },
   "contentRating": "safe",
   "score": 0.1852552,
   "languages": [
    "en"
   ]
  },
  {
   "id": "b4615bd9-7cbd-4243-a8a2-5c24671663e0",
   "title": {
    "en": "Yajin Tensei: Karate Survivor in Another World"
   },
   "contentRating": "safe",
   "score": 0.18394926,
   "languages": [
    "en",
    "pt-br"
   ]
  },
  {
   "id": "f0954799-3cbd-4be0-805e-29161edfa312",
   "title": {
    "en": "Death Edge"
   },
   "contentRating": "safe",
   "score": 0.18324748,
   "languages": [
    "pl",
    "en"
   ]
  },
  {
   "id": "8211bac6-a392-4e37-b3b6-dac0f4512d24",
   "title": {
    "en": "Re:Zero kara Hajimeru Isekai Seikatsu - Daiyonshou - Seiiki to Gouyoku no Majou"
   },
   "contentRating": "safe",
   "score": 0.1794498,
   "languages": [
    "ru",
    "it",
    "en",
    "id",
    "pt-br",
    "es",
    "vi"
   ]
  },
  {
   "id": "635f010e-39e6-491b-9e61-a82af671b52c",
   "title": {
    "en": "Tales of the World - Radiant Mythology"
   },
   "contentRating": "safe",
   "score": 0.17650466,
   "languages": [
    "en"
   ]
  },
  {
   "id": "7b9d73ff-a19e-4817-9eb7-657471f4d8d5",
   "title": {
    "en": "Kinnikuman"
   },
   "contentRating": "safe",
   "score": 0.17634669,
   "languages": [
    "pt-br",
    "en",
    "it"
   ]
  },
  {
   "id": "b5b21ca1-bba5-4b9a-8cd1-6248f731650b",
   "title": {
    "en": "Record of Ragnarok"
   },
   "contentRating": "safe",
   "score": 0.17627518,
   "languages": [
    "zh-hk",
    "en",
    "fr",
    "tr",
    "es-la",
    "ru",
    "pt-br",
    "bg",
    "uk",
    "id",
    "it",
    "vi",
    "fa",
    "ar",
    "pl"
   ]
  },
  {
   "id": "5d1fc77e-706a-4fc5-bea8-486c9be0145d",
   "title": {
    "en": "Vinland Saga"
   },
   "contentRating": "safe",
   "score": 0.17517501,
   "languages": [
    "es-la",
    "en",
    "pt-br",
    "ru",
    "ar",
    "cs",
    "uk",
    "tr",
    "ro",
    "es",
    "it"
   ]
  },
  {
   "id": "38ce723f-6069-4fd7-89c8-b3c6242d96b8",
   "title": {
    "en": "Doku Doku Mori Mori"
   },
   "contentRating": "safe",
   "score": 0.17499548,
   "languages": [
    "pt-br",
    "en"
   ]
  },
  {
   "id": "b46e2e33-b8a6-46cc-9504-b3d4c0ebce35",
   "title": {
    "en": "A Country Without Humans"
   },
   "contentRating": "safe",
   "score": 0.17411502,
   "languages": [
    "en"
   ]
  },
  {
   "id": "0491bc8a-bfaf-4732-9503-3ac5c4208aba",
   "title": {
    "en": "Bigger Hunter"
   },
   "contentRating": "safe",
   "score": 0.1738011,
   "languages": [
    "pl",
    "fr",
    "en"
   ]
  }
 ],
 "updatedAt": "2023-12-10T01:06:38+00:00"
}