{
 "id": "5e16acfe-896a-4f20-8223-482f862107e3",
 "title": {
  "en": "One Day, Suddenly, Seoul Is"
 },
 "contentRating": "safe",
 "matches": [
  {
   "id": "946ff973-95b5-4f57-8e81-7c4674ea50dc",
   "title": {
    "en": "The Druid of Seoul Station"
   },
   "contentRating": "safe",
   "score": 0.2753404,
   "languages": [
    "pl",
    "en",
    "uk",
    "hu"
   ]
  },
  {
   "id": "7901b983-f223-4fd9-bb1f-a42584b4d6ed",
   "title": {
    "en": "Machine Era"
   },
   "contentRating": "safe",
   "score": 0.26177287,
   "languages": [
    "pt-br",
    "en"
   ]
  },
  {
   "id": "ed4ab87b-0364-400a-8241-7ff3c032efb9",
   "title": {
    "en": "Post Pandemic"
   },
   "contentRating": "safe",
   "score": 0.26070815,
   "languages": [
    "en"
   ]
  },
  {
   "id": "1e197b19-c0aa-4529-90f1-7ae3cad41396",
   "title": {
    "en": "App's Orbs"
   },
   "contentRating": "safe",
   "score": 0.24861515,
   "languages": [
    "en"
   ]
  },
  {
   "id": "77a32fb4-a1ff-4200-96fb-45ef4f63fbf4",
   "title": {
    "en": "Devil's Editing"
   },
   "contentRating": "safe",
   "score": 0.24356127,
   "languages": [
    "en"
   ]
  },
  {
   "id": "c0de0416-0937-44c4-98ff-1e76dfa5fd77",
   "title": {
    "en": "Gaek"
   },
   "contentRating": "safe",
   "score": 0.24111666,
   "languages": [
    "en"
   ]
  },
  {
   "id": "467eee07-6c0b-49c5-a1bf-2b5d8686d514",
   "title": {
    "en": "Doom Spore"
   },
   "contentRating": "safe",
   "score": 0.23303384,
   "languages": [
    "en"
   ]
  },
  {
   "id": "2bcdea67-dc36-4d0a-949e-99bb7037912b",
   "title": {
    "en": "The Story of Park's Marriage Contract"
   },
   "contentRating": "safe",
   "score": 0.2262459,
   "languages": [
    "en",
    "my"
   ]
  },
  {
   "id": "f70fa4df-5752-4c78-89b9-c812ff751760",
   "title": {
    "en": "Man on the Mountain"
   },
   "contentRating": "safe",
   "score": 0.22392611,
   "languages": [
    "en"
   ]
  },
  {
   "id": "e6ae7e70-fbdf-4ee5-a1b8-75267e7f17fe",
   "title": {
    "en": "Division 8's Record of Secrets"
   },
   "contentRating": "safe",
   "score": 0.22392611,
   "languages": [
    "en"
   ]
  },
  {
   "id": "05fecbc0-e8f2-4faa-9e56-21d55352fe31",
   "title": {
    "en": "Dark Hole: Another Survivor"
   },
   "contentRating": "safe",
   "score": 0.21530703,
   "languages": [
    "en"
   ]
  },
  {
   "id": "67acf80b-bd6b-44f1-b71c-6e7142c36775",
   "title": {
    "en": "The Soldier King"
   },
   "contentRating": "safe",
   "score": 0.21381442,
   "languages": [
    "en",
    "id"
   ]
  },
  {
   "id": "80d288be-bdb9-4637-804e-02b2f89ad2d8",
   "title": {
    "en": "Jungle Juice"
   },
   "contentRating": "safe",
   "score": 0.21350518,
   "languages": [
    "fa",
    "en",
    "pl",
    "pt-br",
    "fr",
    "id",
    "tr",
    "hu"
   ]
  },
  {
   "id": "338fd64d-37c5-410a-929a-938cda8234e2",
   "title": {
    "en": "The End Of A Relationship"
   },
   "contentRating": "safe",
   "score": 0.21189177,
   "languages": [
    "en"
   ]
  },
  {
   "id": "2e79031f-b2be-4856-9a9c-4dd29501f38a",
   "title": {
    "en": "Resurgence of the Solo Beta Player"
   },
   "contentRating": "safe",
   "score": 0.2102999,
   "languages": [
    "en"
   ]
  },
  {
   "id": "42032393-b80a-4d42-8732-06a028322207",
   "title": {
    "en": "Utori: The Legacy"
   },
   "contentRating": "safe",
   "score": 0.20997602,
   "languages": [
    "en"
   ]
  }
 ],
 "updatedAt": "2023-12-10T01:03:30+00:00"
}