{
 "id": "196745b9-8fae-4880-9afb-aaa713d3440b",
 "title": {
  "en": "Ai no Shittakabutta - Akeru to Kimochi ga Raku ni Naru Hon"
 },
 "contentRating": "safe",
 "matches": [
  {
   "id": "8b8d20cf-c58a-4da4-a9ad-6017b9092c08",
   "title": {
    "en": "Sono Rokudenashi ni You ga Aru"
   },
   "contentRating": "safe",
   "score": 0.32637423,
   "languages": [
    "fr",
    "en"
   ]
  },
  {
   "id": "7c2ab8e0-58e6-4315-93a1-c787ef765751",
   "title": {
    "en": "Aisupe @"
   },
   "contentRating": "safe",
   "score": 0.30461815,
   "languages": [
    "en"
   ]
  },
  {
   "id": "7bba4ac3-5d5c-4456-97d1-104abaa960a7",
   "title": {
    "en": "Jinjya no Susume"
   },
   "contentRating": "safe",
   "score": 0.299675,
   "languages": [
    "en"
   ]
  },
  {
   "id": "d54b5ba8-17c9-4774-8fb9-98593ebdf8e8",
   "title": {
    "en": "Baby, Kokoro no Mama ni!"
   },
   "contentRating": "safe",
   "score": 0.29607034,
   "languages": [
    "id",
    "en",
    "pl",
    "pt-br"
   ]
  },
  {
   "id": "3d2420d7-7a5a-4318-935f-1d3fb35a55db",
   "title": {
    "en": "Sweet Spot"
   },
   "contentRating": "safe",
   "score": 0.28723827,
   "languages": [
    "en"
   ]
  },
  {
   "id": "0697a7ca-c6d1-4704-8630-73503301c316",
   "title": {
    "en": "Nomino"
   },
   "contentRating": "safe",
   "score": 0.2851258,
   "languages": [
    "fr",
    "en"
   ]
  },
  {
   "id": "4c111bd9-7039-4db1-9704-db6a5166f278",
   "title": {
    "en": "Wagahai no Kare wa Baka de aru"
   },
   "contentRating": "safe",
   "score": 0.2851258,
   "languages": [
    "en",
    "vi"
   ]
  },
  {
   "id": "5b409f07-8569-41a7-9abf-fd27b31e575c",
   "title": {
    "en": "Sakaki Mirei no Tame nara Boku wa...!!"
   },
   "contentRating": "safe",
   "score": 0.2851258,
   "languages": [
    "en"
   ]
  },
  {
   "id": "678b336e-22f4-4a6f-86cc-add483fa6023",
   "title": {
    "en": "Conditions to Be a Husband"
   },
   "contentRating": "safe",
   "score": 0.2851258,
   "languages": [
    "en"
   ]
  },
  {
   "id": "cf381a3d-ece9-4ae7-a693-96a49a69908a",
   "title": {
    "en": "Tamariba"
   },
   "contentRating": "safe",
   "score": 0.2851258,
   "languages": [
    "en"
   ]
  },
  {
   "id": "c44b3e3b-a7e0-4101-b43a-6d58768e7726",
   "title": {
    "en": "Ten yori Takaku"
   },
   "contentRating": "safe",
   "score": 0.2851258,
   "languages": [
    "pt-br",
    "en"
   ]
  },
  {
   "id": "a2a1e197-1466-4e7c-9bdb-e8dda4131d61",
   "title": {
    "en": "First Love AI"
   },
   "contentRating": "safe",
   "score": 0.28381053,
   "languages": [
    "en",
    "pt-br"
   ]
  },
  {
   "id": "9964ea10-6a8c-49d5-9a2b-12d72747e721",
   "title": {
    "en": "A Story About Spending a Little More Time With an Eccentric Girl"
   },
   "contentRating": "safe",
   "score": 0.26743338,
   "languages": [
    "fr",
    "id",
    "en",
    "vi",
    "ms",
    "pt-br",
    "ru",
    "th",
    "ro"
   ]
  },
  {
   "id": "10b8bb96-3b6a-4edc-a428-ddd3e88c3a63",
   "title": {
    "en": "Robo Maid ga Kanjou Yutaka ni Naru Hanashi"
   },
   "contentRating": "safe",
   "score": 0.26709026,
   "languages": [
    "en",
    "pl",
    "pt-br",
    "id",
    "kk"
   ]
  },
  {
   "id": "548007e1-a9e4-43dc-8088-c3f3419b4abe",
   "title": {
    "en": "Sukinahito no Tame ni Hentai ni Naru Koto o Kimeta Hanashi"
   },
   "contentRating": "safe",
   "score": 0.2655944,
   "languages": [
    "vi",
    "en",
    "id"
   ]
  },
  {
   "id": "1a1c044f-4cab-468f-ba97-5d53b5ab84c9",
   "title": {
    "en": "Akari of the Forest Bookshop"
   },
   "contentRating": "safe",
   "score": 0.26520085,
   "languages": [
    "en"
   ]
  }
 ],
 "updatedAt": "2023-12-10T01:00:44+00:00"
}