{
 "id": "7cb19254-9b46-4b24-9315-98965cbeb90d",
 "title": {
  "en": "Coulomb Fille"
 },
 "contentRating": "safe",
 "matches": [
  {
   "id": "568d156b-1b9b-4f19-b7e4-0512239d9eb0",
   "title": {
    "en": "Cafe Occult"
   },
   "contentRating": "safe",
   "score": 0.23627761,
   "languages": [
    "en"
   ]
  },
  {
   "id": "c40c0488-627d-49b8-8ff8-a04283700b98",
   "title": {
    "en": "The Chronicle of Seven (webcomic version)"
   },
   "contentRating": "safe",
   "score": 0.20203052,
   "languages": [
    "en"
   ]
  },
  {
   "id": "434fce68-4796-4d43-a38d-f79f0ee9103f",
   "title": {
    "en": "Sono Mukou no Mukougawa"
   },
   "contentRating": "safe",
   "score": 0.19047621,
   "languages": [
    "fr",
    "en"
   ]
  },
  {
   "id": "88000462-085e-45ff-80bd-6d5117387431",
   "title": {
    "en": "Amata"
   },
   "contentRating": "safe",
   "score": 0.19047621,
   "languages": [
    "en",
    "ar"
   ]
  },
  {
   "id": "39f8ef92-d5d7-44e1-8a4e-85db6fc9c42d",
   "title": {
    "en": "GATE 7"
   },
   "contentRating": "safe",
   "score": 0.1870439,
   "languages": [
    "pt-br",
    "en",
    "pl"
   ]
  },
  {
   "id": "f3626de0-f3f5-4b65-957a-a417f8b087df",
   "title": {
    "en": "Rain"
   },
   "contentRating": "safe",
   "score": 0.1870439,
   "languages": [
    "pt-br",
    "ru",
    "en",
    "pl",
    "fr",
    "tr",
    "es-la"
   ]
  },
  {
   "id": "98ce22fd-01aa-48e5-8ded-d96bd438e80f",
   "title": {
    "en": "Star Ocean - The Second Story"
   },
   "contentRating": "safe",
   "score": 0.18257791,
   "languages": [
    "en"
   ]
  },
  {
   "id": "b060460c-18d4-4e43-9ddb-e39343eeed62",
   "title": {
    "en": "Jinrou e no Tensei, Maou no Fukukan: Shidou-hen"
   },
   "contentRating": "safe",
   "score": 0.17731759,
   "languages": [
    "ru",
    "en",
    "fr",
    "pt-br",
    "es"
   ]
  },
  {
   "id": "21b18592-8925-466b-b909-071b52676a38",
   "title": {
    "en": "Teiden Shoujo to Hanemushi no Orchestra"
   },
   "contentRating": "safe",
   "score": 0.17496355,
   "languages": [
    "en"
   ]
  },
  {
   "id": "57749a58-650b-473f-abf0-057da0f40755",
   "title": {
    "en": "Zhan Long"
   },
   "contentRating": "safe",
   "score": 0.17496355,
   "languages": [
    "fr",
    "en",
    "pl"
   ]
  },
  {
   "id": "2036ce4b-46ac-4e88-b0b1-90b3ea3aa1a1",
   "title": {
    "en": "Nante Nasakenai Bokura da"
   },
   "contentRating": "safe",
   "score": 0.17337504,
   "languages": [
    "en",
    "tr",
    "pt-br",
    "ca",
    "zh-hk"
   ]
  },
  {
   "id": "8787958d-a3f1-4d48-8220-fad148c7c28e",
   "title": {
    "en": "Fragment"
   },
   "contentRating": "safe",
   "score": 0.17334378,
   "languages": [
    "en"
   ]
  },
  {
   "id": "fa2363d3-318a-45e7-a597-cea5543aaaf2",
   "title": {
    "en": "THE iDOLM@STER Innocent Blue for Dearly Stars"
   },
   "contentRating": "safe",
   "score": 0.17245902,
   "languages": [
    "en"
   ]
  },
  {
   "id": "70cc8d60-d4a8-4c7e-a1e2-eb8e05ff9c3a",
   "title": {
    "en": "Jinrou e no Tensei, Maou no Fukkan: Hajimari no Shou"
   },
   "contentRating": "safe",
   "score": 0.1694056,
   "languages": [
    "en",
    "fr",
    "id",
    "ru"
   ]
  },
  {
   "id": "24856a89-229a-4cca-9fae-8c70ee1eebd9",
   "title": {
    "en": "Nyan-Nyan Oratorio"
   },
   "contentRating": "safe",
   "score": 0.16495723,
   "languages": [
    "en"
   ]
  },
  {
   "id": "9b0532d7-00ba-4cfd-ba3c-b58c881f571f",
   "title": {
    "en": "Radiata Stories - The Song of Ridley"
   },
   "contentRating": "safe",
   "score": 0.16495723,
   "languages": [
    "en"
   ]
  }
 ],
 "updatedAt": "2023-12-10T01:04:46+00:00"
}