{
 "id": "8971bb40-37b0-49e4-9a28-20cbed0896a5",
 "title": {
  "en": "Tokyo Lastochika"
 },
 "contentRating": "safe",
 "matches": [
  {
   "id": "1631d535-8826-46f7-9a9c-4fc97de2a813",
   "title": {
    "en": "Shoku no Hana"
   },
   "contentRating": "safe",
   "score": 0.25423795,
   "languages": [
    "en"
   ]
  },
  {
   "id": "15a15de0-9acc-46e7-816f-1f328311c700",
   "title": {
    "en": "Hanameguri Awase"
   },
   "contentRating": "safe",
   "score": 0.24860357,
   "languages": [
    "en"
   ]
  },
  {
   "id": "ccd571a0-850d-4b90-a077-53ab0523f008",
   "title": {
    "en": "Hachimitsu no Hana"
   },
   "contentRating": "safe",
   "score": 0.2252176,
   "languages": [
    "pl",
    "en"
   ]
  },
  {
   "id": "0b2beaa6-08df-44e5-a404-ecee109744fc",
   "title": {
    "en": "Candy Candy"
   },
   "contentRating": "safe",
   "score": 0.21550134,
   "languages": [
    "pt-br",
    "en",
    "es"
   ]
  },
  {
   "id": "fb9fb9a7-a661-49ae-a6bb-2d160b105184",
   "title": {
    "en": "Hana-kun to Koisuru Watashi"
   },
   "contentRating": "safe",
   "score": 0.21439008,
   "languages": [
    "pt-br",
    "pl",
    "en"
   ]
  },
  {
   "id": "1d6d98f8-57fb-4608-b127-b365a50760af",
   "title": {
    "en": "Yowamushi Meikyuu"
   },
   "contentRating": "safe",
   "score": 0.21159142,
   "languages": [
    "pt-br",
    "pl"
   ]
  },
  {
   "id": "80c27ff8-7916-4b81-9c0d-cb3d647a24b7",
   "title": {
    "en": "Legend of Nereid"
   },
   "contentRating": "safe",
   "score": 0.20905976,
   "languages": [
    "en",
    "fr"
   ]
  },
  {
   "id": "91705092-a3c2-4e22-a8bb-1e77cf9b18d9",
   "title": {
    "en": "Boku no Mei"
   },
   "contentRating": "safe",
   "score": 0.20905976,
   "languages": [
    "en",
    "pl"
   ]
  },
  {
   "id": "98da2297-1cec-4f2e-be55-bd971a8b95c4",
   "title": {
    "en": "Niji no Ikusa"
   },
   "contentRating": "safe",
   "score": 0.20175427,
   "languages": [
    "en"
   ]
  },
  {
   "id": "8424b171-ec06-432c-bfda-5439244826f7",
   "title": {
    "en": "Cinderella Collection"
   },
   "contentRating": "safe",
   "score": 0.20158304,
   "languages": [
    "en"
   ]
  },
  {
   "id": "db7402a8-547a-451c-ab0c-fe0d395640b8",
   "title": {
    "en": "Room"
   },
   "contentRating": "safe",
   "score": 0.20158304,
   "languages": [
    "en"
   ]
  },
  {
   "id": "a3fab004-1fe5-4cbf-be8f-1a1f538d09d7",
   "title": {
    "en": "Do Not Fight"
   },
   "contentRating": "safe",
   "score": 0.20158304,
   "languages": [
    "en"
   ]
  },
  {
   "id": "fdcb49b8-44de-487a-a1dd-526c5ac9a4f9",
   "title": {
    "en": "Princess"
   },
   "contentRating": "safe",
   "score": 0.19978096,
   "languages": [
    "en"
   ]
  },
  {
   "id": "755bdfd3-0d99-4030-8feb-efe7c0ac8a48",
   "title": {
    "en": "Family!"
   },
   "contentRating": "safe",
   "score": 0.19973391,
   "languages": [
    "en"
   ]
  },
  {
   "id": "6ab88e56-955e-4325-a651-48547a6f0c98",
   "title": {
    "en": "Chotto Edo Made"
   },
   "contentRating": "safe",
   "score": 0.19560753,
   "languages": [
    "en"
   ]
  },
  {
   "id": "d5fc7365-f202-44c6-a029-08ea04896dcc",
   "title": {
    "en": "Liselotte \u0026 the Witch's Forest"
   },
   "contentRating": "safe",
   "score": 0.19548821,
   "languages": [
    "en"
   ]
  }
 ],
 "updatedAt": "2023-12-10T01:05:20+00:00"
}