{
 "id": "90fc0cc0-dba0-43be-a28c-b9ad6b97792a",
 "title": {
  "en": "Chilling Messages"
 },
 "contentRating": "safe",
 "matches": [
  {
   "id": "6576ac4c-0251-4978-ace8-70c675cb3b86",
   "title": {
    "en": "Seeds of Anxiety*"
   },
   "contentRating": "safe",
   "score": 0.26817015
  },
  {
   "id": "e503974f-e397-4ebb-bdf4-62583582ef12",
   "title": {
    "en": "Look Me in the Eyes When You Talk"
   },
   "contentRating": "safe",
   "score": 0.24240315,
   "languages": [
    "it",
    "en",
    "ca"
   ]
  },
  {
   "id": "9adabe75-571b-4811-b543-3d3be83d7baf",
   "title": {
    "en": "He Was My Brother"
   },
   "contentRating": "safe",
   "score": 0.22326991,
   "languages": [
    "en",
    "es-la"
   ]
  },
  {
   "id": "951b95f7-986b-4fd4-89e7-dfc9dfb75e12",
   "title": {
    "en": "Shadowman"
   },
   "contentRating": "safe",
   "score": 0.21844356,
   "languages": [
    "pt-br",
    "es",
    "en"
   ]
  },
  {
   "id": "9ef6e461-033b-4976-b222-943856c94a97",
   "title": {
    "en": "Smiley"
   },
   "contentRating": "safe",
   "score": 0.21758097,
   "languages": [
    "es-la",
    "en",
    "vi",
    "ru"
   ]
  },
  {
   "id": "403721a8-0793-431f-b47c-89eb04f402ae",
   "title": {
    "en": "Ousama Game - Kigen"
   },
   "contentRating": "safe",
   "score": 0.21441731,
   "languages": [
    "es-la"
   ]
  },
  {
   "id": "70281eed-7252-4207-b6a7-71fc6b92eabf",
   "title": {
    "en": "Ishiguro Masakazu's Kyoufu Tanpen"
   },
   "contentRating": "safe",
   "score": 0.21137758,
   "languages": [
    "en"
   ]
  },
  {
   "id": "ea602e52-c61f-48b4-bce2-f3975828220c",
   "title": {
    "en": "The Ring Vol.1"
   },
   "contentRating": "safe",
   "score": 0.20546788
  },
  {
   "id": "d4a49028-1aa5-4422-ad5d-729b20d0dc4f",
   "title": {
    "en": "Jigoku Kurayami Hana mo Naki"
   },
   "contentRating": "safe",
   "score": 0.2017885,
   "languages": [
    "zh",
    "ru",
    "zh-hk",
    "en"
   ]
  },
  {
   "id": "95716c73-f20f-4ac9-96b9-22adfbd0c563",
   "title": {
    "en": "Honogurai Mizu no Soko kara"
   },
   "contentRating": "safe",
   "score": 0.19987284,
   "languages": [
    "en"
   ]
  },
  {
   "id": "2954a23f-22c1-4bce-a2fc-0a0dc3e201a7",
   "title": {
    "en": "PTSD Radio"
   },
   "contentRating": "safe",
   "score": 0.19648476,
   "languages": [
    "pt-br",
    "pl",
    "en",
    "uk"
   ]
  },
  {
   "id": "b32e1324-9e5c-4f19-b5d8-9421510ebc3b",
   "title": {
    "en": "Kakeru"
   },
   "contentRating": "safe",
   "score": 0.19584092,
   "languages": [
    "en"
   ]
  },
  {
   "id": "96045bc1-004e-42df-8d4f-f4ffd7ec317a",
   "title": {
    "en": "The Dream I Had When I Died"
   },
   "contentRating": "safe",
   "score": 0.19584092,
   "languages": [
    "pt-br",
    "en"
   ]
  },
  {
   "id": "beaa5eda-ddff-4d05-a890-97abc78f05e2",
   "title": {
    "en": "Signal 100 Zero"
   },
   "contentRating": "safe",
   "score": 0.19584092
  },
  {
   "id": "43e0daab-eda3-4ae2-bf2c-5fe4bf19fb7c",
   "title": {
    "en": "Koukai no Naraku"
   },
   "contentRating": "safe",
   "score": 0.19180173,
   "languages": [
    "en",
    "pl"
   ]
  },
  {
   "id": "0eec92db-2b8a-4d80-8e13-4afc9e353b00",
   "title": {
    "en": "Kyuubi: Choujou Jiken Taisakuka"
   },
   "contentRating": "safe",
   "score": 0.18308346
  }
 ],
 "updatedAt": "2023-12-10T01:05:42+00:00"
}