{
 "id": "c1c73616-5d33-4868-9b91-31cd633e53ab",
 "title": {
  "en": "F.O.X II"
 },
 "contentRating": "safe",
 "matches": [
  {
   "id": "0f66d44c-7577-4a14-a7ce-76c8872afb86",
   "title": {
    "en": "Fox Concubine, Don’t Play With Fire"
   },
   "contentRating": "safe",
   "score": 0.43382898,
   "languages": [
    "en",
    "hu"
   ]
  },
  {
   "id": "985f013f-5c34-4b5a-a549-8a35cb0c284f",
   "title": {
    "en": "Divine Melody"
   },
   "contentRating": "safe",
   "score": 0.40000138,
   "languages": [
    "hu",
    "pl"
   ]
  },
  {
   "id": "edfc095d-7867-4dac-9a45-5429c3f009b7",
   "title": {
    "en": "Oh, My Romantic Kumiho"
   },
   "contentRating": "safe",
   "score": 0.30840555,
   "languages": [
    "en"
   ]
  },
  {
   "id": "9daea609-0bcf-448f-96fe-bbab7eb12751",
   "title": {
    "en": "Kirara☆Princess"
   },
   "contentRating": "safe",
   "score": 0.29364935
  },
  {
   "id": "8409d47d-31a0-4765-b985-9bd82b3e60d3",
   "title": {
    "en": "Shirokuro Tsukeru?"
   },
   "contentRating": "safe",
   "score": 0.2857143
  },
  {
   "id": "5b2f1b53-25a8-4fa3-b355-3a24db87e3da",
   "title": {
    "en": "Cynical Master Raises Rabbit Spirit"
   },
   "contentRating": "safe",
   "score": 0.27918366,
   "languages": [
    "en"
   ]
  },
  {
   "id": "06020d3e-3f5a-4d18-bc73-6d12acda0370",
   "title": {
    "en": "Kiss Happiness Kiss"
   },
   "contentRating": "safe",
   "score": 0.26356438,
   "languages": [
    "pl",
    "en"
   ]
  },
  {
   "id": "24983d6d-f51b-4c53-9a2d-c2c64d903a67",
   "title": {
    "en": "Angel Myth"
   },
   "contentRating": "safe",
   "score": 0.26032725,
   "languages": [
    "en"
   ]
  },
  {
   "id": "9552f227-b3db-4e6c-8d54-60197d439d94",
   "title": {
    "en": "Little Witch's Diary"
   },
   "contentRating": "safe",
   "score": 0.25863445
  },
  {
   "id": "2ac33039-13f4-4dd1-bbb6-72c0393327ed",
   "title": {
    "en": "Tsukuroiya"
   },
   "contentRating": "safe",
   "score": 0.24910174,
   "languages": [
    "en"
   ]
  },
  {
   "id": "42894459-c805-4110-a332-00d4bc9bff39",
   "title": {
    "en": "Tobenai Washi Ouji"
   },
   "contentRating": "safe",
   "score": 0.24743582,
   "languages": [
    "pl",
    "en"
   ]
  },
  {
   "id": "dd01b0e5-2fe2-4ca0-8ceb-ca69ecc9471d",
   "title": {
    "en": "Tsubasa o Motsu Mono"
   },
   "contentRating": "safe",
   "score": 0.24743582,
   "languages": [
    "en"
   ]
  },
  {
   "id": "b3dfbe4f-830c-4d88-89cf-7e8d6332ef64",
   "title": {
    "en": "Piyo Piyo Tenshi"
   },
   "contentRating": "safe",
   "score": 0.23328476,
   "languages": [
    "ru"
   ]
  },
  {
   "id": "e509dab4-ee9d-443e-903a-2c175f374b99",
   "title": {
    "en": "B-Wanted"
   },
   "contentRating": "safe",
   "score": 0.23328476,
   "languages": [
    "en",
    "it"
   ]
  },
  {
   "id": "cd324a28-9dea-4273-ad31-2633f8aaf98e",
   "title": {
    "en": "Other Side of the Milky Way"
   },
   "contentRating": "safe",
   "score": 0.23328476,
   "languages": [
    "en"
   ]
  },
  {
   "id": "802051c6-59d2-477c-a10a-f21ca08db6da",
   "title": {
    "en": "Engage Knight"
   },
   "contentRating": "safe",
   "score": 0.23328476
  }
 ],
 "updatedAt": "2023-12-10T01:07:45+00:00"
}