{
 "id": "6f29e83f-04b1-490a-ae48-2e88ab93849d",
 "title": {
  "en": "Facade"
 },
 "contentRating": "safe",
 "matches": [
  {
   "id": "ef2549f8-b34d-4ed2-869d-b4d4b991c44d",
   "title": {
    "en": "Patrol QT"
   },
   "contentRating": "safe",
   "score": 0.26803112
  },
  {
   "id": "781cbd86-ed40-4ed9-a766-ebeeb5270847",
   "title": {
    "en": "Kijimutan"
   },
   "contentRating": "safe",
   "score": 0.2326995
  },
  {
   "id": "57642280-65de-4879-a6e2-2e0420237369",
   "title": {
    "en": "Tenkuu Seiryuu ~Innocent Dragon~"
   },
   "contentRating": "safe",
   "score": 0.23248002,
   "languages": [
    "en",
    "it"
   ]
  },
  {
   "id": "7852e93b-8efa-4443-8329-9248639dcfb7",
   "title": {
    "en": "Moon-Ah"
   },
   "contentRating": "safe",
   "score": 0.22882213,
   "languages": [
    "en"
   ]
  },
  {
   "id": "e8baba85-9eac-447c-9a3b-ef4af41ddf82",
   "title": {
    "en": "Dragon Fist"
   },
   "contentRating": "safe",
   "score": 0.22703116,
   "languages": [
    "en"
   ]
  },
  {
   "id": "ba89c653-d57d-4523-8b8c-880134054e13",
   "title": {
    "en": "Tableau Gate"
   },
   "contentRating": "safe",
   "score": 0.2211598
  },
  {
   "id": "5baa3347-0e37-40c0-8177-5972706c85de",
   "title": {
    "en": "Ryuu no Nemuru Hoshi"
   },
   "contentRating": "safe",
   "score": 0.2208736
  },
  {
   "id": "3e1f12de-d97d-4baa-b701-0987ab2e1bb3",
   "title": {
    "en": "Aries"
   },
   "contentRating": "safe",
   "score": 0.22044748,
   "languages": [
    "en"
   ]
  },
  {
   "id": "dd01b0e5-2fe2-4ca0-8ceb-ca69ecc9471d",
   "title": {
    "en": "Tsubasa o Motsu Mono"
   },
   "contentRating": "safe",
   "score": 0.2194004,
   "languages": [
    "en"
   ]
  },
  {
   "id": "bf44b0a9-707c-4bcd-9c0c-e8cc195ff926",
   "title": {
    "en": "Prince of the Night"
   },
   "contentRating": "safe",
   "score": 0.21937768,
   "languages": [
    "en"
   ]
  },
  {
   "id": "89c51c81-c890-41c3-a512-30a838df9e04",
   "title": {
    "en": "Itihasa"
   },
   "contentRating": "safe",
   "score": 0.21881469
  },
  {
   "id": "9dfebf18-2e8e-4f2e-978c-9cb1f9e8f773",
   "title": {
    "en": "Hana no Utage"
   },
   "contentRating": "safe",
   "score": 0.21655965
  },
  {
   "id": "416e9b22-ea7a-4ac5-98f2-fe63c49dec8a",
   "title": {
    "en": "Otogi Moyou Ayanishiki Futatabi"
   },
   "contentRating": "safe",
   "score": 0.20687605,
   "languages": [
    "en",
    "es"
   ]
  },
  {
   "id": "a7982a3a-8fd5-4e42-b6ad-c1ea47c4f7c1",
   "title": {
    "en": "Xue Lian"
   },
   "contentRating": "safe",
   "score": 0.20644996
  },
  {
   "id": "d99c7d70-1c52-4699-adde-c07043565951",
   "title": {
    "en": "Sarasah"
   },
   "contentRating": "safe",
   "score": 0.20644996,
   "languages": [
    "en"
   ]
  },
  {
   "id": "59fba7da-5364-47a4-9c62-678ba7822b96",
   "title": {
    "en": "Harukanaru Toki no Naka de"
   },
   "contentRating": "safe",
   "score": 0.20614679,
   "languages": [
    "en"
   ]
  }
 ],
 "updatedAt": "2023-12-10T01:04:11+00:00"
}