{
 "id": "39cb5817-e559-425b-bba3-cea656a6fd87",
 "title": {
  "en": "Otome wa Inoru - Himitsu no Dormitory"
 },
 "contentRating": "safe",
 "matches": [
  {
   "id": "2d4c05a1-8fc2-4dbd-955a-1c8a6bd5fa03",
   "title": {
    "en": "Secret Dance"
   },
   "contentRating": "safe",
   "score": 0.24977191,
   "languages": [
    "en"
   ]
  },
  {
   "id": "28501b32-5d9f-4926-a484-ca775a2b063b",
   "title": {
    "en": "Ichigo to Anzu"
   },
   "contentRating": "safe",
   "score": 0.24692619,
   "languages": [
    "en"
   ]
  },
  {
   "id": "27fe5a83-23ce-4a6e-8c88-8e3c10799402",
   "title": {
    "en": "Tsumi to Bachi"
   },
   "contentRating": "safe",
   "score": 0.24532536,
   "languages": [
    "en"
   ]
  },
  {
   "id": "22d86b53-9cd8-40a9-b941-1e03d0f84744",
   "title": {
    "en": "Hana no Niwa Ame no Mai"
   },
   "contentRating": "safe",
   "score": 0.23809525,
   "languages": [
    "en"
   ]
  },
  {
   "id": "f8a82dd6-88a0-4e61-b09d-47be1e6b6ee7",
   "title": {
    "en": "Take Off"
   },
   "contentRating": "safe",
   "score": 0.21035548,
   "languages": [
    "pt-br",
    "pl",
    "en"
   ]
  },
  {
   "id": "2124b898-a137-4592-9431-2a9e1ab3ab00",
   "title": {
    "en": "Jane and Harlequin"
   },
   "contentRating": "safe",
   "score": 0.20819306,
   "languages": [
    "en"
   ]
  },
  {
   "id": "18ef6f62-d72f-4d8b-b734-efc8ee8d52d2",
   "title": {
    "en": "Twink Twink"
   },
   "contentRating": "safe",
   "score": 0.207393,
   "languages": [
    "en"
   ]
  },
  {
   "id": "21a8efa7-8b64-41de-b61c-b4f94e2aed62",
   "title": {
    "en": "Chibi Maruko-chan"
   },
   "contentRating": "safe",
   "score": 0.20507137,
   "languages": [
    "en"
   ]
  },
  {
   "id": "fb9fb9a7-a661-49ae-a6bb-2d160b105184",
   "title": {
    "en": "Hana-kun to Koisuru Watashi"
   },
   "contentRating": "safe",
   "score": 0.2027055,
   "languages": [
    "pt-br",
    "pl",
    "en"
   ]
  },
  {
   "id": "784614ea-949f-43ed-952f-9881677aa477",
   "title": {
    "en": "Dog and My Family Circumstance"
   },
   "contentRating": "safe",
   "score": 0.20161438,
   "languages": [
    "ru",
    "en"
   ]
  },
  {
   "id": "e96064cb-0f58-40ae-a19c-d70deca1fa77",
   "title": {
    "en": "Mikami-kun no Himitsu"
   },
   "contentRating": "safe",
   "score": 0.19838668,
   "languages": [
    "pl",
    "en"
   ]
  },
  {
   "id": "eaa718b1-af3b-4b36-aa8a-77d5852ba0b7",
   "title": {
    "en": "The Microcosm Among Us Is Much Further Ahead"
   },
   "contentRating": "safe",
   "score": 0.19440396,
   "languages": [
    "en"
   ]
  },
  {
   "id": "dbc280ae-48b9-43d5-acbb-a0ec5abd2fa4",
   "title": {
    "en": "Bye Bye, Ame."
   },
   "contentRating": "safe",
   "score": 0.19440396,
   "languages": [
    "pt-br",
    "en"
   ]
  },
  {
   "id": "aeed5d3a-094b-4422-a03c-b136aeb0d2ad",
   "title": {
    "en": "Tenkousei, Ridatsu Suru"
   },
   "contentRating": "safe",
   "score": 0.19440396,
   "languages": [
    "en"
   ]
  },
  {
   "id": "cd37dec0-2a85-48d2-b7a5-a092161965b6",
   "title": {
    "en": "Nekomori-kun no Himitsu no Tobira"
   },
   "contentRating": "safe",
   "score": 0.19019142,
   "languages": [
    "pl",
    "en"
   ]
  },
  {
   "id": "b5594eff-90e2-4e66-b328-c5c78ddd0637",
   "title": {
    "en": "Kagehinata"
   },
   "contentRating": "safe",
   "score": 0.18437073,
   "languages": [
    "en"
   ]
  }
 ],
 "updatedAt": "2023-12-10T01:01:58+00:00"
}