{
 "id": "8443de98-4d05-40e1-a84f-d54905fbb563",
 "title": {
  "en": "Kanaria-tachi no Fune"
 },
 "contentRating": "safe",
 "matches": [
  {
   "id": "b6356e8e-5550-45a1-bb6e-205e00dd27d3",
   "title": {
    "en": "Nightmare Busters"
   },
   "contentRating": "safe",
   "score": 0.26833764,
   "languages": [
    "zh-hk",
    "en"
   ]
  },
  {
   "id": "3617aaec-946c-4957-83a1-599c559669b4",
   "title": {
    "en": "Ultra Heaven"
   },
   "contentRating": "safe",
   "score": 0.2547755,
   "languages": [
    "en",
    "pt-br"
   ]
  },
  {
   "id": "c4b1cb49-46e9-405d-8b48-8104de22e659",
   "title": {
    "en": "Cosmos"
   },
   "contentRating": "safe",
   "score": 0.22153787,
   "languages": [
    "es",
    "fr",
    "pt-br",
    "en"
   ]
  },
  {
   "id": "f3a7a5e3-487d-433c-916b-bcaeccad5f6c",
   "title": {
    "en": "Deep Love - Real"
   },
   "contentRating": "safe",
   "score": 0.21648477,
   "languages": [
    "en"
   ]
  },
  {
   "id": "a3ec539f-d2b5-4889-a50b-de6142b45b6d",
   "title": {
    "en": "Kokushi no Shima"
   },
   "contentRating": "safe",
   "score": 0.20210184,
   "languages": [
    "en"
   ]
  },
  {
   "id": "9ed7759e-3a3e-4850-b1ef-0b039add6f75",
   "title": {
    "en": "Alien 9 Complete"
   },
   "contentRating": "safe",
   "score": 0.19656895,
   "languages": [
    "en"
   ]
  },
  {
   "id": "49e0e6a2-d567-4f4b-93c3-cc30faa58529",
   "title": {
    "en": "Cloud"
   },
   "contentRating": "safe",
   "score": 0.19518936,
   "languages": [
    "en"
   ]
  },
  {
   "id": "02be54ac-b1bc-496c-a496-bcea5356bcb5",
   "title": {
    "en": "Do You Know the Real Dangers of Those So-Called Legal Drugs that are Being Sold?"
   },
   "contentRating": "safe",
   "score": 0.19132291,
   "languages": [
    "en"
   ]
  },
  {
   "id": "7bf8351e-4190-4ec6-be39-bbd8489ec8ad",
   "title": {
    "en": "Seikai Suru Kado"
   },
   "contentRating": "safe",
   "score": 0.18678425,
   "languages": [
    "en"
   ]
  },
  {
   "id": "e81ea7de-f614-4652-83ed-3c29f77acb5e",
   "title": {
    "en": "Vampir"
   },
   "contentRating": "safe",
   "score": 0.18054742,
   "languages": [
    "en"
   ]
  },
  {
   "id": "45013df7-7a13-429b-acd2-53a086b2ef92",
   "title": {
    "en": "Atrocious Fairy Tales for Adults"
   },
   "contentRating": "safe",
   "score": 0.17706263,
   "languages": [
    "en"
   ]
  },
  {
   "id": "d2d7dd16-7e7b-4bf8-8f61-0e3c0f38437a",
   "title": {
    "en": "Uncanny Brains"
   },
   "contentRating": "safe",
   "score": 0.17676179,
   "languages": [
    "en"
   ]
  },
  {
   "id": "07e67401-a3b5-47dc-adc1-205f5cae6e10",
   "title": {
    "en": "Nightmares"
   },
   "contentRating": "safe",
   "score": 0.17634669,
   "languages": [
    "en",
    "it"
   ]
  },
  {
   "id": "dc22c201-a2a8-40aa-a23f-69852b0c8d0f",
   "title": {
    "en": "Kowloon Generic Romance"
   },
   "contentRating": "safe",
   "score": 0.17634669,
   "languages": [
    "pt-br",
    "es-la",
    "zh-hk",
    "en",
    "ru"
   ]
  },
  {
   "id": "9df240b5-b551-4220-80db-6dd9de413e26",
   "title": {
    "en": "Horobi no Mae no Shangri-La"
   },
   "contentRating": "safe",
   "score": 0.17634669,
   "languages": [
    "en"
   ]
  },
  {
   "id": "e95a7130-933a-4d31-b812-5ff476c1c5a7",
   "title": {
    "en": "Sherlock"
   },
   "contentRating": "safe",
   "score": 0.17496355,
   "languages": [
    "en",
    "tr"
   ]
  }
 ],
 "updatedAt": "2023-12-10T01:05:05+00:00"
}