{
 "id": "71f26724-3a3f-43e7-9758-15f27effc136",
 "title": {
  "en": "Valkyrie Resistance: Origins"
 },
 "contentRating": "safe",
 "matches": [
  {
   "id": "36014191-132e-46ad-ba20-a3ccf9487d5c",
   "title": {
    "en": "Valkyrie Profile 2"
   },
   "contentRating": "safe",
   "score": 0.2701779,
   "languages": [
    "en"
   ]
  },
  {
   "id": "8477d4e3-fab7-422b-b6fe-c699ec5f5789",
   "title": {
    "en": "Arata Kangatari"
   },
   "contentRating": "safe",
   "score": 0.24381061,
   "languages": [
    "en",
    "pl"
   ]
  },
  {
   "id": "5ccca4ae-c54a-4b20-aadb-c822f1fa2960",
   "title": {
    "en": "Outbreak Company: Moeru Shinryakusha"
   },
   "contentRating": "safe",
   "score": 0.23180641,
   "languages": [
    "en"
   ]
  },
  {
   "id": "62483bf6-e4c2-4aaf-bf53-fc822ba21428",
   "title": {
    "en": "Knight Run - Father's Day"
   },
   "contentRating": "safe",
   "score": 0.2299638,
   "languages": [
    "en"
   ]
  },
  {
   "id": "d281d203-531d-440d-9b27-40e208063a6a",
   "title": {
    "en": "FUTURE STAY ROUTE - Guardiantales"
   },
   "contentRating": "safe",
   "score": 0.22707458,
   "languages": [
    "en",
    "ru"
   ]
  },
  {
   "id": "7d24ea7b-d4e1-4aa5-a26a-9dd1b32edb2b",
   "title": {
    "en": "Arcana 11 - Time Travel / Time Traveller"
   },
   "contentRating": "safe",
   "score": 0.22147842,
   "languages": [
    "en"
   ]
  },
  {
   "id": "229eb307-021e-4062-8d39-94422da2671e",
   "title": {
    "en": "Tail Star"
   },
   "contentRating": "safe",
   "score": 0.21937384,
   "languages": [
    "pl",
    "en",
    "es",
    "pt-br"
   ]
  },
  {
   "id": "45aa8f26-3985-4c9a-bd2b-40c3e1242a77",
   "title": {
    "en": "Heroes of the Spring and Autumn"
   },
   "contentRating": "safe",
   "score": 0.21069306,
   "languages": [
    "en"
   ]
  },
  {
   "id": "09a5f228-f6b2-42a0-9d37-f661ebc6ad35",
   "title": {
    "en": "Hatenkou Yuugi"
   },
   "contentRating": "safe",
   "score": 0.20714049,
   "languages": [
    "en",
    "pl"
   ]
  },
  {
   "id": "dc2d3f4d-db09-4167-929d-4800b33ea92d",
   "title": {
    "en": "Arashi no Hana Murakumo no Uta"
   },
   "contentRating": "safe",
   "score": 0.20521615,
   "languages": [
    "en"
   ]
  },
  {
   "id": "390009ac-c723-43d6-a146-84129eeddb93",
   "title": {
    "en": "Yongbyeong Maluhan"
   },
   "contentRating": "safe",
   "score": 0.20501591,
   "languages": [
    "en",
    "ar"
   ]
  },
  {
   "id": "fdcb49b8-44de-487a-a1dd-526c5ac9a4f9",
   "title": {
    "en": "Princess"
   },
   "contentRating": "safe",
   "score": 0.20316356,
   "languages": [
    "en"
   ]
  },
  {
   "id": "a025d065-ec7f-4962-a874-45903f5dc618",
   "title": {
    "en": "Valkyrie Profile - The Dark Alchemist"
   },
   "contentRating": "safe",
   "score": 0.20218614,
   "languages": [
    "en"
   ]
  },
  {
   "id": "568d156b-1b9b-4f19-b7e4-0512239d9eb0",
   "title": {
    "en": "Cafe Occult"
   },
   "contentRating": "safe",
   "score": 0.20203735,
   "languages": [
    "en"
   ]
  },
  {
   "id": "c7d93139-b172-42d9-b5d8-56c0cdb606a3",
   "title": {
    "en": "City Hunter - Rebirth"
   },
   "contentRating": "safe",
   "score": 0.20170711,
   "languages": [
    "en",
    "es-la"
   ]
  },
  {
   "id": "3f14383c-de77-4b9f-94ba-28421c2ea419",
   "title": {
    "en": "The Transmigrated Mage Life in Another World, Becoming the Strongest in the World with the Knowledge of the Original Story"
   },
   "contentRating": "safe",
   "score": 0.20061785,
   "languages": [
    "en"
   ]
  }
 ],
 "updatedAt": "2023-12-10T01:04:18+00:00"
}