{
 "id": "eab0c11e-b65a-4658-98fa-6e618208252d",
 "title": {
  "en": "Pokémon Diamond and Pearl"
 },
 "contentRating": "safe",
 "matches": [
  {
   "id": "9216a467-b6c0-40e1-9e39-877b3c7b0f1c",
   "title": {
    "en": "Get Pokémon!"
   },
   "contentRating": "safe",
   "score": 0.38362572,
   "languages": [
    "en"
   ]
  },
  {
   "id": "3d87d62a-c520-4a7a-9595-e3d27c526c1d",
   "title": {
    "en": "Pokémon Card GB The Comix"
   },
   "contentRating": "safe",
   "score": 0.34013522,
   "languages": [
    "en"
   ]
  },
  {
   "id": "eba9285c-8314-4f14-898d-a9476b83a394",
   "title": {
    "en": "Pokémon"
   },
   "contentRating": "safe",
   "score": 0.33794546,
   "languages": [
    "en"
   ]
  },
  {
   "id": "7eb0e395-5754-4e0a-bbc7-1b883de9e641",
   "title": {
    "en": "Pokémon HeartGold SoulSilver: Go! Go! Pokéathlon"
   },
   "contentRating": "safe",
   "score": 0.3189802,
   "languages": [
    "pt-br",
    "en",
    "uk"
   ]
  },
  {
   "id": "b009f62d-7a65-417d-990a-2e671b036069",
   "title": {
    "en": "Pokémon: Mewtwo Strikes Back!"
   },
   "contentRating": "safe",
   "score": 0.29105437,
   "languages": [
    "pl",
    "en"
   ]
  },
  {
   "id": "4cb44f68-779b-4c7f-bf3d-acb1fef83944",
   "title": {
    "en": "Pokémon Mystery Dungeon: Explorers of Time and Darkness"
   },
   "contentRating": "safe",
   "score": 0.2602975,
   "languages": [
    "en"
   ]
  },
  {
   "id": "587d905c-7b4a-401b-a23b-946535ce4d5d",
   "title": {
    "en": "Alien Nine Special"
   },
   "contentRating": "safe",
   "score": 0.24718568,
   "languages": [
    "en"
   ]
  },
  {
   "id": "1306adc1-8e8e-45df-ac54-d02e86eabd58",
   "title": {
    "en": "Noisy! Wario"
   },
   "contentRating": "safe",
   "score": 0.23833914,
   "languages": [
    "en"
   ]
  },
  {
   "id": "41797f21-635f-428d-8a71-78c25ed11b46",
   "title": {
    "en": "Mega Man Battle Network Operate Shooting Star VS"
   },
   "contentRating": "safe",
   "score": 0.23623982,
   "languages": [
    "es-la",
    "en"
   ]
  },
  {
   "id": "65a0e567-5db6-46ac-bdef-b6ae3da3e9ff",
   "title": {
    "en": "Memories with Oda-san's Manga!"
   },
   "contentRating": "safe",
   "score": 0.22250836,
   "languages": [
    "en",
    "ca"
   ]
  },
  {
   "id": "523ac7ed-0b24-4598-b440-814d8bdcf540",
   "title": {
    "en": "Soul Land II - The Peerless Tang Sect"
   },
   "contentRating": "safe",
   "score": 0.21926416,
   "languages": [
    "pt-br",
    "en",
    "fr",
    "it"
   ]
  },
  {
   "id": "057f5360-c37c-4619-a6a4-cb5aea7f5f6a",
   "title": {
    "en": "The Legend of Zelda - Skyward Sword"
   },
   "contentRating": "safe",
   "score": 0.21545653,
   "languages": [
    "en",
    "ca",
    "pt-br"
   ]
  },
  {
   "id": "3805fc64-44f0-46b6-b972-5c14ce7e856c",
   "title": {
    "en": "Maple Purple"
   },
   "contentRating": "safe",
   "score": 0.21407081,
   "languages": [
    "en",
    "pt-br"
   ]
  },
  {
   "id": "d414a39d-d525-456e-be84-17b1d8cbb5fe",
   "title": {
    "en": "Kono Subarashii Sekai ni Shukufuku o! Fantastic Days!"
   },
   "contentRating": "safe",
   "score": 0.21282353,
   "languages": [
    "en"
   ]
  },
  {
   "id": "e6e0b418-ca33-4919-8b62-50aa28908dc7",
   "title": {
    "en": "Mega Man: The Deadly Struggle on Mu Arc"
   },
   "contentRating": "safe",
   "score": 0.20853072,
   "languages": [
    "en",
    "es"
   ]
  },
  {
   "id": "3a2c5a51-7fab-4427-bd3f-46cd0aa6350d",
   "title": {
    "en": "Saint Seiya - Shura vs Tenma vs Shoko!! Shugeki Battle Royale Hen"
   },
   "contentRating": "safe",
   "score": 0.20818658,
   "languages": [
    "pt-br",
    "en"
   ]
  }
 ],
 "updatedAt": "2023-12-10T01:09:27+00:00"
}