{
 "id": "da229b4e-7722-40e2-8c0b-4def041fe884",
 "title": {
  "en": "Tegami Bachi"
 },
 "contentRating": "safe",
 "matches": [
  {
   "id": "4e9ac5e9-7eaa-4bc6-be4a-98e849dcd60c",
   "title": {
    "en": "Hero"
   },
   "contentRating": "safe",
   "score": 0.27384904,
   "languages": [
    "pl",
    "en"
   ]
  },
  {
   "id": "463b32af-1ddc-48db-a5e4-4799c8a2e412",
   "title": {
    "en": "Rakshasa Street"
   },
   "contentRating": "safe",
   "score": 0.24489798,
   "languages": [
    "fr",
    "en",
    "pl",
    "pt-br"
   ]
  },
  {
   "id": "ddc1f94d-08f7-474e-9e2e-4f2bc06d8df3",
   "title": {
    "en": "Segregated World"
   },
   "contentRating": "safe",
   "score": 0.24147265,
   "languages": [
    "en"
   ]
  },
  {
   "id": "34e45b02-b5c8-4a4b-a21a-7b5059391dc8",
   "title": {
    "en": "To Your Eternity"
   },
   "contentRating": "safe",
   "score": 0.23716289,
   "languages": [
    "ru",
    "pt-br",
    "es",
    "en",
    "es-la",
    "tr",
    "mn",
    "uk"
   ]
  },
  {
   "id": "7e04ffec-28b0-4594-b796-68bb056d87b0",
   "title": {
    "en": "Tales of Destiny 2"
   },
   "contentRating": "safe",
   "score": 0.21920145,
   "languages": [
    "en"
   ]
  },
  {
   "id": "3b7a12a9-c86d-4092-800b-ca3bfaa8d5f9",
   "title": {
    "en": "Tales of Phantasia"
   },
   "contentRating": "safe",
   "score": 0.21597971,
   "languages": [
    "en"
   ]
  },
  {
   "id": "97d299f1-1c93-4146-8ac2-7238a59d49bf",
   "title": {
    "en": "Gwisin Byeolgok"
   },
   "contentRating": "safe",
   "score": 0.20489633,
   "languages": [
    "en"
   ]
  },
  {
   "id": "39f8ef92-d5d7-44e1-8a4e-85db6fc9c42d",
   "title": {
    "en": "GATE 7"
   },
   "contentRating": "safe",
   "score": 0.20408164,
   "languages": [
    "pt-br",
    "en",
    "pl"
   ]
  },
  {
   "id": "bbe605e5-bbe6-4091-bb6b-e8aa8dbf8fe6",
   "title": {
    "en": "Gyakushuu no Dragon Rider"
   },
   "contentRating": "safe",
   "score": 0.20346974,
   "languages": [
    "en"
   ]
  },
  {
   "id": "678e3447-37cc-4205-bdc0-c67b933670e7",
   "title": {
    "en": "Mononoke Hime"
   },
   "contentRating": "safe",
   "score": 0.20325018,
   "languages": [
    "en"
   ]
  },
  {
   "id": "f8781b2c-7677-44d1-a0b4-b2a3c4752601",
   "title": {
    "en": "Naruto Gaiden: Michita Tsuki ga Terasu Michi"
   },
   "contentRating": "safe",
   "score": 0.19565259,
   "languages": [
    "en"
   ]
  },
  {
   "id": "11c0eb33-5206-4a79-bd4a-ba45620a2096",
   "title": {
    "en": "Toshokan Sensou - SPITFIRE!"
   },
   "contentRating": "safe",
   "score": 0.19317813,
   "languages": [
    "en"
   ]
  },
  {
   "id": "3e0b9d06-cf97-4c12-9e0b-f6e41a72181b",
   "title": {
    "en": "Stray Dog"
   },
   "contentRating": "safe",
   "score": 0.19317813,
   "languages": [
    "en",
    "it",
    "pt-br",
    "fr"
   ]
  },
  {
   "id": "dee582b2-2633-4287-86c5-e7a9e51e8bba",
   "title": {
    "en": "Yuusha Goikkou no Kaerimichi"
   },
   "contentRating": "safe",
   "score": 0.19317813,
   "languages": [
    "en",
    "es-la",
    "ru",
    "zh-hk",
    "id",
    "tr",
    "vi",
    "uk",
    "fr",
    "pt-br"
   ]
  },
  {
   "id": "5b585d5a-95ce-427e-bd02-054cab289bdc",
   "title": {
    "en": "Desert Tribe"
   },
   "contentRating": "safe",
   "score": 0.19317813,
   "languages": [
    "en"
   ]
  },
  {
   "id": "fbfe07a9-4b54-4a4f-a43c-da39eba8bd14",
   "title": {
    "en": "Wizardry Zeo"
   },
   "contentRating": "safe",
   "score": 0.19317813,
   "languages": [
    "en"
   ]
  }
 ],
 "updatedAt": "2023-12-10T01:08:46+00:00"
}