{
 "id": "0fa92925-5509-44d2-9976-981f07411aaf",
 "title": {
  "en": "Nise x Koi Boyfriend - Henshin Shichau (Doujinshi)"
 },
 "contentRating": "safe",
 "matches": [
  {
   "id": "25693a60-f21a-4e41-8914-b192e64e37a7",
   "title": {
    "en": "Free! - Kyou wa Otomari na no de. (Doujinshi)"
   },
   "contentRating": "safe",
   "score": 0.27083737,
   "languages": [
    "tr",
    "en"
   ]
  },
  {
   "id": "677c7d7a-b462-4d88-87a5-a81f2ba9c02e",
   "title": {
    "en": "Kuroko no Basuke - Aomine Birthday Paper (Doujinshi)"
   },
   "contentRating": "safe",
   "score": 0.25540477,
   "languages": [
    "en",
    "hu"
   ]
  },
  {
   "id": "a3e74c90-7ff3-4e26-b4c9-6ccb216edef7",
   "title": {
    "en": "Free! - Soshite Koi o Shiru (Doujinshi)"
   },
   "contentRating": "safe",
   "score": 0.2504722,
   "languages": [
    "tr",
    "en"
   ]
  },
  {
   "id": "8db746da-372c-4645-81ee-69914a6bcd88",
   "title": {
    "en": "Free! - Bokutachi no, Koi no Hajimari (Doujinshi)"
   },
   "contentRating": "safe",
   "score": 0.2432467,
   "languages": [
    "en"
   ]
  },
  {
   "id": "ce7eb2bb-c8b2-41f1-8ca0-a1aed3b1fc86",
   "title": {
    "en": "Kuroko no Basuke - Akashi-sama no lu Toori (Doujinshi)"
   },
   "contentRating": "safe",
   "score": 0.2426679,
   "languages": [
    "en"
   ]
  },
  {
   "id": "2d2fb80d-b8b4-47a3-b381-2ef6c2eb6958",
   "title": {
    "en": "Code Geass - Heaven's Garden (Doujinshi)"
   },
   "contentRating": "safe",
   "score": 0.24104406,
   "languages": [
    "en"
   ]
  },
  {
   "id": "72b01556-4d7f-4f78-bb6b-3f22952ce742",
   "title": {
    "en": "Kuroko no Basuke  - Tenshi no OO (Doujinshi)"
   },
   "contentRating": "safe",
   "score": 0.23545767,
   "languages": [
    "en",
    "tr"
   ]
  },
  {
   "id": "7fd489ce-d390-4945-8557-376cee220ab8",
   "title": {
    "en": "Toy Box (Naf Naf-Re)"
   },
   "contentRating": "safe",
   "score": 0.23363197,
   "languages": [
    "en"
   ]
  },
  {
   "id": "08b06a9e-9858-4c2f-8989-7231398a8939",
   "title": {
    "en": "Haikyuu!! - A Date, Right?! (Doujinshi)"
   },
   "contentRating": "safe",
   "score": 0.23043971,
   "languages": [
    "ca",
    "uk",
    "en"
   ]
  },
  {
   "id": "fbaa7215-cee2-4b90-b833-a575af6c2eaf",
   "title": {
    "en": "Sis-con"
   },
   "contentRating": "safe",
   "score": 0.23013805,
   "languages": [
    "en"
   ]
  },
  {
   "id": "02e9d99f-bd00-4ce7-9e5c-0d9a976c7f39",
   "title": {
    "en": "Bleach - After Iris (Doujinshi)"
   },
   "contentRating": "safe",
   "score": 0.22965911,
   "languages": [
    "en"
   ]
  },
  {
   "id": "f29b09a5-1c24-449d-b319-b4d2c60d3a61",
   "title": {
    "en": "Yakusoku"
   },
   "contentRating": "safe",
   "score": 0.22853369,
   "languages": [
    "en",
    "it"
   ]
  },
  {
   "id": "925bc33a-56b6-495a-8389-147b3ff48367",
   "title": {
    "en": "Code Geass - Dearest (Doujinshi)"
   },
   "contentRating": "safe",
   "score": 0.22750728,
   "languages": [
    "en"
   ]
  },
  {
   "id": "48220f11-2cf9-4733-accc-6807fef3ff34",
   "title": {
    "en": "Bleach - Adabana (Doujinshi)"
   },
   "contentRating": "safe",
   "score": 0.22578217,
   "languages": [
    "en"
   ]
  },
  {
   "id": "595e3a7a-c762-4f87-90ee-a7dc0dabef91",
   "title": {
    "en": "Tennis no Oujisama - Onecoin Reserve (Doujinshi)"
   },
   "contentRating": "safe",
   "score": 0.22474259,
   "languages": [
    "en"
   ]
  },
  {
   "id": "f7f5eb88-fd6e-477d-801d-536e78790220",
   "title": {
    "en": "Magi - The Color of Loving Someone (Doujinshi)"
   },
   "contentRating": "safe",
   "score": 0.22443265,
   "languages": [
    "en"
   ]
  }
 ],
 "updatedAt": "2023-12-10T01:00:22+00:00"
}