{
 "id": "cb21fb37-80a6-4a47-a643-709384ffcf65",
 "title": {
  "en": "R★P Roman Porn"
 },
 "contentRating": "erotica",
 "matches": [
  {
   "id": "00e97789-3a25-4804-a8e7-37527280c4b8",
   "title": {
    "en": "Isekai AV Satsueitai: Remaster"
   },
   "contentRating": "erotica",
   "score": 0.36041048
  },
  {
   "id": "58c8d732-eb5c-4d32-b875-05a6149db975",
   "title": {
    "en": "Want to Learn Sex From a Pro? ~Sweet Touches Until You Want More"
   },
   "contentRating": "erotica",
   "score": 0.35698143,
   "languages": [
    "en"
   ]
  },
  {
   "id": "eaa7c1db-c8b4-4ec8-aa12-afc19c7959a8",
   "title": {
    "en": "Boku ga Gay-Vi Danyuu ni Natta Riyuu"
   },
   "contentRating": "erotica",
   "score": 0.35630193,
   "languages": [
    "en"
   ]
  },
  {
   "id": "ebb9621c-84ed-4f50-8144-dac8df075285",
   "title": {
    "en": "Ghost Gate"
   },
   "contentRating": "erotica",
   "score": 0.34421277,
   "languages": [
    "en"
   ]
  },
  {
   "id": "8570d80e-6446-49f0-8cd1-b972a021b290",
   "title": {
    "en": "Fever Flower"
   },
   "contentRating": "erotica",
   "score": 0.34402478,
   "languages": [
    "en"
   ]
  },
  {
   "id": "448524ff-1b68-4c2a-9e42-928fa7362692",
   "title": {
    "en": "10 Oku-en no Keiyaku Hanayome"
   },
   "contentRating": "erotica",
   "score": 0.34277102
  },
  {
   "id": "c1d39d55-5683-45a8-85a2-4f434c0471e1",
   "title": {
    "en": "Buchou to Shachiku no Koi wa Modokashii"
   },
   "contentRating": "erotica",
   "score": 0.33858415
  },
  {
   "id": "b44565f2-e1e8-400a-9b42-983832e44c15",
   "title": {
    "en": "The Voices That Call Me"
   },
   "contentRating": "erotica",
   "score": 0.337646,
   "languages": [
    "it",
    "en"
   ]
  },
  {
   "id": "ec805f9e-7ee1-46ff-a04d-48427d9027b7",
   "title": {
    "en": "An Engagement without Dating with My Scion Childhood Friend: A Lovey-Dovey Life Even with a Contract Marriage!?"
   },
   "contentRating": "erotica",
   "score": 0.3361952
  },
  {
   "id": "f9c94566-0262-4bd1-96a3-6f87a316d325",
   "title": {
    "en": "Camera no Mukou de Mesu ni Naru"
   },
   "contentRating": "erotica",
   "score": 0.33400226
  },
  {
   "id": "35c558d8-bb99-4e04-8318-c3283ccbb258",
   "title": {
    "en": "Toraware Hime"
   },
   "contentRating": "erotica",
   "score": 0.33305702
  },
  {
   "id": "9cd2542a-8c17-47fb-bac8-b6c6b6624cc5",
   "title": {
    "en": "Gold Gray"
   },
   "contentRating": "erotica",
   "score": 0.3306153,
   "languages": [
    "id"
   ]
  },
  {
   "id": "b1b36105-5734-4a64-83f9-121fd7cf2ec5",
   "title": {
    "en": "Did You Do Naughty Things with My Voice?"
   },
   "contentRating": "erotica",
   "score": 0.32869604
  },
  {
   "id": "8f449877-8abf-499d-9dfd-92a18c5c58b1",
   "title": {
    "en": "Suteishi Yuusha, Maou no Shita de Restart"
   },
   "contentRating": "erotica",
   "score": 0.32732433,
   "languages": [
    "en",
    "th",
    "id",
    "pt-br"
   ]
  },
  {
   "id": "b1ede308-344f-494b-9f9e-2ee60b9291d8",
   "title": {
    "en": "Souai Blue Marriage"
   },
   "contentRating": "erotica",
   "score": 0.3265684
  },
  {
   "id": "6603f4aa-c893-4f6e-837e-ec6c4c6baa77",
   "title": {
    "en": "Her Toy Shop"
   },
   "contentRating": "erotica",
   "score": 0.32647035
  }
 ],
 "updatedAt": "2023-12-10T01:08:08+00:00"
}