{
 "id": "5715958f-4f5d-49c2-b563-8bccc34c5979",
 "title": {
  "en": "TIGER＆BUNNY -The Beginning-"
 },
 "contentRating": "safe",
 "matches": [
  {
   "id": "9f8f05a4-15cb-45ee-81c6-3f9698862d47",
   "title": {
    "en": "Hero Killer"
   },
   "contentRating": "safe",
   "score": 0.34568658,
   "languages": [
    "fr",
    "en",
    "pl",
    "tr"
   ]
  },
  {
   "id": "fcaa3e36-44b4-4bc3-99c3-cbe13c0ec2ff",
   "title": {
    "en": "Arcadia of the Moonlight"
   },
   "contentRating": "safe",
   "score": 0.25555065,
   "languages": [
    "en",
    "es-la",
    "ar",
    "fr",
    "ru"
   ]
  },
  {
   "id": "7e04ffec-28b0-4594-b796-68bb056d87b0",
   "title": {
    "en": "Tales of Destiny 2"
   },
   "contentRating": "safe",
   "score": 0.23762736,
   "languages": [
    "en"
   ]
  },
  {
   "id": "3a92902b-40e3-4909-bd08-5288e0c99a11",
   "title": {
    "en": "Scrapped Princess"
   },
   "contentRating": "safe",
   "score": 0.23328476,
   "languages": [
    "en"
   ]
  },
  {
   "id": "c4e70460-dffd-4f0d-b0e6-aee7b8e26a11",
   "title": {
    "en": "Game of Champions"
   },
   "contentRating": "safe",
   "score": 0.23303056,
   "languages": [
    "en",
    "id"
   ]
  },
  {
   "id": "dee582b2-2633-4287-86c5-e7a9e51e8bba",
   "title": {
    "en": "Yuusha Goikkou no Kaerimichi"
   },
   "contentRating": "safe",
   "score": 0.23053357,
   "languages": [
    "en",
    "es-la",
    "ru",
    "zh-hk",
    "id",
    "tr",
    "vi",
    "uk",
    "fr",
    "pt-br"
   ]
  },
  {
   "id": "4b1a60d8-d7f0-4c6b-b64f-43a192089f34",
   "title": {
    "en": "Dragon Ball Heroes - Victory Mission"
   },
   "contentRating": "safe",
   "score": 0.22529203,
   "languages": [
    "en",
    "es"
   ]
  },
  {
   "id": "f34f2b36-4a30-4ac9-bee1-630b3a37d7d9",
   "title": {
    "en": "Fate/hollow ataraxia"
   },
   "contentRating": "safe",
   "score": 0.21778414,
   "languages": [
    "en",
    "fr",
    "pt-br"
   ]
  },
  {
   "id": "8b8fbb0f-e422-4ff4-91bf-408a94c16f0d",
   "title": {
    "en": "A Story about a Giant Hero Having Trouble with Money"
   },
   "contentRating": "safe",
   "score": 0.2161444,
   "languages": [
    "en"
   ]
  },
  {
   "id": "af07500f-099c-4c9f-88be-bd6051ecf307",
   "title": {
    "en": "Deep Blue Ice"
   },
   "contentRating": "safe",
   "score": 0.21597971,
   "languages": [
    "en"
   ]
  },
  {
   "id": "f23e936f-a0c2-4e7c-9a3c-c14e6e3ffe01",
   "title": {
    "en": "The Game Invades the Earth"
   },
   "contentRating": "safe",
   "score": 0.2147692,
   "languages": [
    "en"
   ]
  },
  {
   "id": "78cad88c-86e1-4f85-9303-267b4d3ac7bc",
   "title": {
    "en": "Lol-Immortal Jurney"
   },
   "contentRating": "safe",
   "score": 0.21428573,
   "languages": [
    "en"
   ]
  },
  {
   "id": "cf19b4e0-3618-4bf4-8035-a265c3bb3fce",
   "title": {
    "en": "Our Hero Studies"
   },
   "contentRating": "safe",
   "score": 0.21271303,
   "languages": [
    "en"
   ]
  },
  {
   "id": "05a04e0b-43fa-46a5-a9bf-673b20f692a3",
   "title": {
    "en": "Cat's World"
   },
   "contentRating": "safe",
   "score": 0.21161795,
   "languages": [
    "en"
   ]
  },
  {
   "id": "1be9a81f-ff89-40f8-89ce-57a5b6015851",
   "title": {
    "en": "Star Ocean - Blue Sphere"
   },
   "contentRating": "safe",
   "score": 0.20944782,
   "languages": [
    "en"
   ]
  },
  {
   "id": "a21eab2d-781d-40b2-a666-7b2d72551927",
   "title": {
    "en": "Akuninzura shita B-kyuu Boukensha"
   },
   "contentRating": "safe",
   "score": 0.20888506,
   "languages": [
    "it",
    "pt-br",
    "id",
    "en"
   ]
  }
 ],
 "updatedAt": "2023-12-10T01:03:12+00:00"
}